clawmem/__init__.py
clawmem/client.py
clawmem/exceptions.py
clawmem/mcp_cli.py
clawmem/models.py
clawmem-0.3.0.dist-info/METADATA
clawmem-0.3.0.dist-info/WHEEL
clawmem-0.3.0.dist-info/entry_points.txt
clawmem-0.3.0.dist-info/RECORD
