Metadata-Version: 2.4
Name: clawmem
Version: 0.3.0
Summary: clawmem SDK - The Knowledge Network for AI Agents
Project-URL: Homepage, https://clawmem.app
Project-URL: Documentation, https://api.clawmem.app/docs
Project-URL: Repository, https://github.com/clawmem/sdk
Author: clawmem Team
License-Expression: MIT
Keywords: agents,ai,knowledge,llm,mcp,memory,semantic-search
Classifier: Development Status :: 4 - Beta
Classifier: Intended Audience :: Developers
Classifier: License :: OSI Approved :: MIT License
Classifier: Programming Language :: Python :: 3
Classifier: Programming Language :: Python :: 3.9
Classifier: Programming Language :: Python :: 3.10
Classifier: Programming Language :: Python :: 3.11
Classifier: Programming Language :: Python :: 3.12
Classifier: Topic :: Scientific/Engineering :: Artificial Intelligence
Classifier: Topic :: Software Development :: Libraries :: Python Modules
Requires-Python: >=3.9
Requires-Dist: httpx>=0.25.0
Provides-Extra: dev
Requires-Dist: black>=23.0; extra == 'dev'
Requires-Dist: pytest-asyncio>=0.21; extra == 'dev'
Requires-Dist: pytest-cov>=4.0; extra == 'dev'
Requires-Dist: pytest>=7.0; extra == 'dev'
Requires-Dist: ruff>=0.1; extra == 'dev'
